<?xml version="1.0" encoding="utf-8"?>
<LanguageData>
<ARA_Basic_Start_Scenario.label>New Arachnid Beehive</ARA_Basic_Start_Scenario.label>
<ARA_Basic_Start_Scenario.description>The Arachne Insect Empress has descended upon the desolate Rimworld, preparing to begin building her own nest.</ARA_Basic_Start_Scenario.description>
<ARA_Basic_Start_Scenario.scenario.name>New Arachnid Beehive</ARA_Basic_Start_Scenario.scenario.name>
<ARA_Basic_Start_Scenario.scenario.description>The Arachne Insect Empress has descended upon the desolate Rimworld, preparing to begin building her own nest.</ARA_Basic_Start_Scenario.scenario.description>
<ARA_Basic_Start_Scenario.scenario.summary>You start the game with one Empress of the Arachne Bug race as the initial settler. There are four Arachne Bug egg sacs at the beginning.</ARA_Basic_Start_Scenario.scenario.summary>
<ARA_Basic_Start_Scenario.scenario.parts.GameStartDialog.text>The Empress species has arrived at the designated area.\nPlanetary environment inspection: habitable.\nBiomass resources: Abundant.\nLocal native civilization: Threat level - low.\nNeural network reconstruction complete. Welcome to join 'us'.\n\nInitial directive:\nEnsure the survival of the Empress species. This is the backbone.\nIncubate the Arachne insect eggs and increase the population of the insect population here.\nAssimilate the biomass of this area and stock up on materials that will ensure the survival of the insect population.\nRebuild the gene tree and make 'us' whole again.\n\nFor the survival of the hive.</ARA_Basic_Start_Scenario.scenario.parts.GameStartDialog.text>
</LanguageData>
