<?xml version="1.0" encoding="utf-8"?>
<LanguageData>

  <ARA_Incubate>Incubate {0}</ARA_Incubate>
  <ARA_NeedsInteraction>Not incubating, requires Arachnae Queen interaction</ARA_NeedsInteraction>

  <ARA_BindDrone_Success>{0} successfully bound to {1}'s Hive Mind.</ARA_BindDrone_Success>
  <ARA_BindDrone_Failure>Could not bind {0} to {1}'s Hive Mind.</ARA_BindDrone_Failure>
  <ARA_BindDrone_NoDroneHediff>Target {0} is not an Arachnae Drone, or does not require a link.</ARA_BindDrone_NoDroneHediff>
  <ARA_BindDrone_AlreadyBound>Target {0} is already bound to {1}.</ARA_BindDrone_AlreadyBound>
  <ARA_BindDrone_NoMasterHediff>Caster {0} is not an Arachnae Queen.</ARA_BindDrone_NoMasterHediff>
  
    <ARA_MustBeHumanlike>Target must be humanlike.</ARA_MustBeHumanlike>
  <ARA_AlreadyPossessed>{0} is already possessed.</ARA_AlreadyPossessed>
  <ARA_CannotPossessRace>Cannot possess {0} race.</ARA_CannotPossessRace>

  <ARA_TipString_LinkedTo>Linked to: {0}</ARA_TipString_LinkedTo>
  <ARA_TipString_NotLinked>Not linked to any Queen.</ARA_TipString_NotLinked>
  <ARA_TipString_ControlledDrones>Controlled Drones:</ARA_TipString_ControlledDrones>
  <ARA_TipString_NoDronesBound>No Drones bound yet.</ARA_TipString_NoDronesBound>

  <MessageTrapSprung>{TRAP} sprung by {PAWN}!</MessageTrapSprung>
  <MessageTrapSprung_NoInstigator>{TRAP} sprung!</MessageTrapSprung_NoInstigator>

  <delivery>{PAWN} generated {THING}.</delivery>

  <AbilitySkillChanged>{USER_labelShort} evolved, changing {1} skill from level {2} to level {3}, and modified passion.</AbilitySkillChanged>

  <AbilityMustBeOnTerrain>Must be on {0} to use this ability.</AbilityMustBeOnTerrain>
  <AbilityDisabledNotOnTerrain>Not on {0}</AbilityDisabledNotOnTerrain>
  <AbilityTerrainRestrictionTip>Can only be used on the following terrain: {0}</AbilityTerrainRestrictionTip>

  <AbilitySkillDurationBonus>Extended by {2} seconds based on {0} skill (level {1}), total duration: {3} seconds</AbilitySkillDurationBonus>

  <AbilityCheckSafeTemperatureRangeLabel>Safe Temperature Range</AbilityCheckSafeTemperatureRangeLabel>
  <AbilityCheckSafeTemperatureRange>{0}°C - {1}°C</AbilityCheckSafeTemperatureRange>
  <AbilityCheckCurrentTemperature>Current Temperature: {0}°C ({1})</AbilityCheckCurrentTemperature>
  <AbilityCheckTemperatureTooLow>Too Low</AbilityCheckTemperatureTooLow>
  <AbilityCheckTemperatureTooHigh>Too High</AbilityCheckTemperatureTooHigh>
  <AbilityCheckTemperatureSafe>Safe</AbilityCheckTemperatureSafe>

  <CocoonRuinedByTemperature>Living structure ruined by extreme temperature</CocoonRuinedByTemperature>
  
  <WillDestroyBodyPart>Will destroy: {0}</WillDestroyBodyPart>
  <CasterDead>Caster is dead</CasterDead>
  <NoValidBodyParts>No valid body parts to destroy</NoValidBodyParts>

  <DisallowedItems>Disallowed Items</DisallowedItems>
  <CannotUseDisallowedFuel>{0} cannot be used as fuel for {1}</CannotUseDisallowedFuel>
  
  <ARA_NeedCost_RequiresAtLeast>Requires at least {0} {1}</ARA_NeedCost_RequiresAtLeast>
  <ARA_NeedCost_Consumption>{0} consumption</ARA_NeedCost_Consumption>
  <ARA_NeedCost_Cost>Cost: {0}</ARA_NeedCost_Cost>
  <ARA_NeedCost_Current>Current: {0}/{1}</ARA_NeedCost_Current>
  <ARA_NeedCost_Insufficient>Insufficient {0}</ARA_NeedCost_Insufficient>
  <ARA_NeedCost_CanCast>Can Cast</ARA_NeedCost_CanCast>

  <PrisonerPlacedInRefuelingVat>Placed {0} into extraction vat.</PrisonerPlacedInRefuelingVat>


  <FuelProduction>Resource Production</FuelProduction>
  <ProductionEfficiency>Production Efficiency</ProductionEfficiency>
  <FuelTankFull>Resource Tank Full</FuelTankFull>
  <CurrentFuel>Current Stored Resource</CurrentFuel>
  <AcidDamageProgress>Progress to next prey damage</AcidDamageProgress>
  <RefuelingVatIdle>Building idle - Place non-Arachnae colonists, captives, and prisoners to produce fuel</RefuelingVatIdle>
  <RefuelingStopped>Production stopped</RefuelingStopped>
  <InsertPersonRefuelingVatDesc>Select a colonist, prisoner, or slave to place them in the extraction vat, where they will slowly take damage to produce resources.</InsertPersonRefuelingVatDesc>
  <AssignCarryPrisoner>Assign Carrier for Prisoner/Slave</AssignCarryPrisoner>
  <AssignCarryPrisonerDesc>Select a Swarm member to take the prisoner or slave to the Arachnae building</AssignCarryPrisonerDesc>
  <NoAvailableHiveCarriers>No available Swarm members to carry the prisoner</NoAvailableHiveCarriers>
  <CarrierAssigned>Assigned {0} to transport {1} to the living structure</CarrierAssigned>
  <NoAvailableCarriers>No available Swarm member carriers</NoAvailableCarriers>
  <NoPrisonersOrSlaves>No available prisoners or slaves</NoPrisonersOrSlaves>

  <StartResearchProduction>Incubate blueprint for {0}</StartResearchProduction>
  <ProducingTechprint>Generating blueprint: {0}</ProducingTechprint>
  <TechprintsToProduce>Blueprints to produce</TechprintsToProduce>
  <ResearchAlreadyCompleted>Research already completed</ResearchAlreadyCompleted>
  <ARA_TechprintCount>Produces {0} blueprints</ARA_TechprintCount>
  <ARA_NeedSpecificArachnaeToStartResearchProduction>Requires {0} to start research production</ARA_NeedSpecificArachnaeToStartResearchProduction>
  <researchProjectsAvailable>Available research projects</researchProjectsAvailable>
  <ARA_TechprintProductionComplete>Production complete: {0} {1} ({2} required for research)</ARA_TechprintProductionComplete>
</LanguageData>